LICENSE.txt
MANIFEST.in
README
README.md
setup.py
MqttSqliteLogger.egg-info/PKG-INFO
MqttSqliteLogger.egg-info/SOURCES.txt
MqttSqliteLogger.egg-info/dependency_links.txt
MqttSqliteLogger.egg-info/entry_points.txt
MqttSqliteLogger.egg-info/requires.txt
MqttSqliteLogger.egg-info/top_level.txt
mqttsqlite/__init__.py
mqttsqlite/__main__.py
mqttsqlite/mqttsqlite.py
mqttsqlite/core/__init__.py
mqttsqlite/core/logs_controller.py
mqttsqlite/core/mqtt_controller.py
mqttsqlite/core/topics_controller.py
mqttsqlite/core/utils.py
mqttsqlite/orm/__init__.py
mqttsqlite/orm/models.py
mqttsqlite/settings/__init__.py
mqttsqlite/settings/private_settings.py
tests/__init__.py
tests/test_logs.py
tests/test_mqtt_controller.py
tests/test_topics.py
tests/utils.py