Metadata-Version: 1.0
Name: MqttSqliteLogger
Version: 1.0
Summary: Simple Sqlite logger for MQTT Brokers.
Home-page: https://github.com/rdiaz82/mqttSqlLite
Author: Roberto Diaz Ortega
Author-email: info@rdiaz.es
License: UNKNOWN
Platform: UNKNOWN
